aserial/__init__.py
aserial-0.1.0.dist-info/METADATA
aserial-0.1.0.dist-info/WHEEL
aserial-0.1.0.dist-info/RECORD
